Metadata-Version: 2.1
Name: phabricator-task-links-mkdocs-plugin
Version: 0.1.0
Summary: This plugin will create links when using Phabricator task numbers
Home-page: https://github.com/theskumar/autolink-references-mkdocs-plugin
Author: Daniel Palstra
Author-email: noreply@danielpalstra.github.com
License: MIT
Platform: UNKNOWN
